odoo9_addon_stock_scanner_location_info-9.0.1.0.0-py2.7-nspkg.pth
odoo_addons/stock_scanner_location_info/__openerp__.py
odoo_addons/stock_scanner_location_info/__init__.py
odoo_addons/stock_scanner_location_info/README.rst
odoo_addons/stock_scanner_location_info/data/Stock.scenario
odoo_addons/stock_scanner_location_info/data/Location_informations/Location_informations.scenario
odoo_addons/stock_scanner_location_info/data/Location_informations/scanner_scenario_step_location_informations_informations_display.py
odoo_addons/stock_scanner_location_info/data/Location_informations/scanner_scenario_step_location_informations_location_selection.py
odoo_addons/stock_scanner_location_info/data/Location_informations/scanner_scenario_step_location_informations_unknown_location.py
odoo_addons/stock_scanner_location_info/images/scenario.png
odoo9_addon_stock_scanner_location_info-9.0.1.0.0.dist-info/top_level.txt
odoo9_addon_stock_scanner_location_info-9.0.1.0.0.dist-info/WHEEL
odoo9_addon_stock_scanner_location_info-9.0.1.0.0.dist-info/RECORD
odoo9_addon_stock_scanner_location_info-9.0.1.0.0.dist-info/metadata.json
odoo9_addon_stock_scanner_location_info-9.0.1.0.0.dist-info/DESCRIPTION.rst
odoo9_addon_stock_scanner_location_info-9.0.1.0.0.dist-info/METADATA
odoo9_addon_stock_scanner_location_info-9.0.1.0.0.dist-info/namespace_packages.txt
